wiki_tool.py
osrs_wiki_cli-1.0.0.dist-info/licenses/LICENSE
osrs_wiki_cli-1.0.0.dist-info/METADATA
osrs_wiki_cli-1.0.0.dist-info/WHEEL
osrs_wiki_cli-1.0.0.dist-info/entry_points.txt
osrs_wiki_cli-1.0.0.dist-info/top_level.txt
osrs_wiki_cli-1.0.0.dist-info/RECORD
