Metadata-Version: 2.4
Name: osrs-wiki-cli
Version: 1.0.0
Summary: Modern CLI utility for extracting structured data from Old School RuneScape Wiki
Home-page: https://github.com/cloud-aspect/osrs-wiki-cli
Author: cloud-aspect
Author-email: 
Maintainer: cloud-aspect
License: MIT License
Project-URL: Homepage, https://github.com/cloud-aspect/osrs-wiki-cli
Project-URL: Repository, https://github.com/cloud-aspect/osrs-wiki-cli.git
Project-URL: Issues, https://github.com/cloud-aspect/osrs-wiki-cli/issues
Project-URL: Documentation, https://github.com/cloud-aspect/osrs-wiki-cli/blob/main/docs/README.md
Keywords: osrs,runescape,wiki,cli,data-extraction,mediawiki,runelite,gaming-tools
Classifier: Development Status :: 4 - Beta
Classifier: Environment :: Console
Classifier: Intended Audience :: Developers
Classifier: License :: OSI Approved :: MIT License
Classifier: Operating System :: OS Independent
Classifier: Programming Language :: Python :: 3
Classifier: Programming Language :: Python :: 3.8
Classifier: Programming Language :: Python :: 3.9
Classifier: Programming Language :: Python :: 3.10
Classifier: Programming Language :: Python :: 3.11
Classifier: Topic :: Games/Entertainment
Classifier: Topic :: Internet :: WWW/HTTP :: Dynamic Content
Classifier: Topic :: Software Development :: Libraries :: Python Modules
Classifier: Topic :: Utilities
Requires-Python: >=3.8
License-File: LICENSE
Requires-Dist: requests>=2.31.0
Requires-Dist: beautifulsoup4>=4.12.2
Dynamic: home-page
Dynamic: license-file
Dynamic: requires-python
